gbdvalidation/__init__.py
gbdvalidation/engine.py
gbdvalidation/execs.py
gbdvalidation/rules/__init__.py
gbdvalidation/rules/codes.py
gbdvalidation/rules/filters.py
gbdvalidation/rules/rules.delete.tmpl
gbdvalidation/rules/rules.tmpl
gbdvalidation/rules/definitions/__init__.py
gbdvalidation/rules/definitions/ao.tmpl
gbdvalidation/rules/definitions/deleted.tmpl
gbdvalidation/rules/definitions/design.tmpl
gbdvalidation/rules/definitions/emblem.tmpl
gbdvalidation/rules/definitions/gi.tmpl
gbdvalidation/rules/definitions/inn.tmpl
gbdvalidation/rules/definitions/trademark.tmpl
wipo_gbd_validation-2.0.5.dist-info/METADATA
wipo_gbd_validation-2.0.5.dist-info/WHEEL
wipo_gbd_validation-2.0.5.dist-info/entry_points.txt
wipo_gbd_validation-2.0.5.dist-info/top_level.txt
wipo_gbd_validation-2.0.5.dist-info/RECORD
