Metadata-Version: 2.4
Name: wipo-gbd-validation
Version: 2.0.5
Summary: GBD validation package
Home-page: https://github.com/GBD-Wipo/gbd-validation
Author: WIPO GDB team
Author-email: gbd@wipo.int
Keywords: gbdtransformation
Classifier: Programming Language :: Python :: 3.9
Requires-Dist: jinja2==2.11.2
Requires-Dist: xmltodict>=0.12.0
Requires-Dist: munch>=2.5.0
Dynamic: author
Dynamic: author-email
Dynamic: classifier
Dynamic: description
Dynamic: home-page
Dynamic: keywords
Dynamic: requires-dist
Dynamic: summary
